flask_spaproxy/__init__.py
flask_spaproxy/reverse_proxy.py
flask_spaproxy/spa_proxy.py
flask_spaproxy/utils.py
Flask_SpaProxy-0.2.dist-info/LICENSE
Flask_SpaProxy-0.2.dist-info/METADATA
Flask_SpaProxy-0.2.dist-info/WHEEL
Flask_SpaProxy-0.2.dist-info/top_level.txt
Flask_SpaProxy-0.2.dist-info/RECORD
