Metadata-Version: 2.1
Name: Flask-SpaProxy
Version: 0.2
Summary: UNKNOWN
Home-page: UNKNOWN
License: MIT license
Platform: UNKNOWN
Classifier: Framework :: Flask
Classifier: Programming Language :: Python :: 3
Classifier: License :: OSI Approved :: MIT License
Classifier: Operating System :: OS Independent
Classifier: Intended Audience :: Developers
License-File: LICENSE
Requires-Dist: flask
Requires-Dist: requests
Provides-Extra: dev
Requires-Dist: alfred-cli ; extra == 'dev'
Requires-Dist: build ; extra == 'dev'
Requires-Dist: pylint ; extra == 'dev'
Requires-Dist: coverage ; extra == 'dev'
Requires-Dist: twine ; extra == 'dev'
